verilog/32_bit_RCA-bottum_up/fulladder.v
module fulladder(a,b,cin,sum,cout);
input a,b,cin;
output sum,cout;

assign sum=a^b^cin;
assign cout=(a&b)|(a&cin)|(b&cin);

endmodule

verilog/32_bit_RCA-bottum_up/fulladder_tb.v
`include "fulladder.v"

module top;
reg a,b,cin;
wire sum,cout;

fulladder FullAdd_0 (a,b,cin,sum,cout);

initial
begin
    a=0;b=0;cin=0;
	#10 b=1;
	#10 a=1;b=0;
	#10 b=1;
    #10 a=0;b=0;cin=1;
    #10 b=1;
	#10 a=1;b=0;
	#10 b=1;
    #10;
end

initial

begin
    $monitor($time,"  a = %b, b = %b, cin = %b sum = %b, cout = %b",a,b,cin,sum,cout);
    $dumpfile("fulladder.vcd");
	$dumpvars;
end

endmodule

verilog/32_bit_RCA-bottum_up/fulladder.vcd
$date
	Thu Aug 20 17:25:25 2020
$end
$version
	Icarus Verilog
$end
$timescale
	1s
$end
$scope module top $end
$var wire 1 ! sum $end
$var wire 1 " cout $end
$var reg 1 # a $end
$var reg 1 $ b $end
$var reg 1 % cin $end
$scope module FullAdd_0 $end
$var wire 1 # a $end
$var wire 1 $ b $end
$var wire 1 % cin $end
$var wire 1 " cout $end
$var wire 1 ! sum $end
$upscope $end
$upscope $end
$enddefinitions $end
#0
$dumpvars
0%
0$
0#
0"
0!
$end
#10
1!
1$
#20
0$
1#
#30
1"
0!
1$
#40
0"
1!
1%
0$
0#
#50
0!
1"
1$
#60
0$
1#
#70
1!
1$
